eelale/__init__.py
eelale/builder.py
eelale/cli.py
eelale-0.3.0.dev0.dist-info/DESCRIPTION.rst
eelale-0.3.0.dev0.dist-info/METADATA
eelale-0.3.0.dev0.dist-info/RECORD
eelale-0.3.0.dev0.dist-info/WHEEL
eelale-0.3.0.dev0.dist-info/entry_points.txt
eelale-0.3.0.dev0.dist-info/metadata.json
eelale-0.3.0.dev0.dist-info/top_level.txt
