Metadata-Version: 2.0
Name: eelale
Version: 0.3.0.dev0
Summary: cross-compiles Python wheels
Home-page: http://github.com/emulbreh/eelale/
Author: Johannes Dollinger
Author-email: emulbreh@googlemail.com
License: BSD License
Platform: UNKNOWN
Classifier: Development Status :: 3 - Alpha
Classifier: Intended Audience :: Developers
Classifier: License :: OSI Approved :: BSD License
Classifier: Operating System :: OS Independent
Classifier: Programming Language :: Python :: 3
Requires-Dist: click
